silent_speech/__init__.py
silent_speech/main.py
silent_speech-0.1.3.dist-info/licenses/LICENSE
silent_speech-0.1.3.dist-info/METADATA
silent_speech-0.1.3.dist-info/WHEEL
silent_speech-0.1.3.dist-info/entry_points.txt
silent_speech-0.1.3.dist-info/top_level.txt
silent_speech-0.1.3.dist-info/RECORD
