Metadata-Version: 2.4
Name: silent-speech
Version: 0.1.3
Summary: Real-time audio visualization and voice-to-text chat interface with Gemini AI
Home-page: https://github.com/laspencer91/silent-speech
Author: Silent Speech Team
Author-email: info@silentspeech.dev
Project-URL: Bug Reports, https://github.com/laspencer91/silent-speech/issues
Project-URL: Source, https://github.com/laspencer91/silent-speech
Keywords: speech-to-text,audio,gemini,ai,voice,transcription,terminal,cli
Classifier: Development Status :: 4 - Beta
Classifier: Intended Audience :: Developers
Classifier: Intended Audience :: End Users/Desktop
Classifier: Topic :: Multimedia :: Sound/Audio :: Speech
Classifier: Topic :: Scientific/Engineering :: Human Machine Interfaces
Classifier: License :: OSI Approved :: MIT License
Classifier: Programming Language :: Python :: 3
Classifier: Programming Language :: Python :: 3.8
Classifier: Programming Language :: Python :: 3.9
Classifier: Programming Language :: Python :: 3.10
Classifier: Programming Language :: Python :: 3.11
Classifier: Operating System :: OS Independent
Classifier: Environment :: Console
Requires-Python: >=3.8
License-File: LICENSE
Requires-Dist: sounddevice>=0.4.6
Requires-Dist: pyperclip>=1.8.2
Requires-Dist: rich>=13.0.0
Requires-Dist: numpy>=1.21.0
Requires-Dist: requests>=2.28.0
Dynamic: author
Dynamic: author-email
Dynamic: classifier
Dynamic: description
Dynamic: description-content-type
Dynamic: home-page
Dynamic: keywords
Dynamic: license-file
Dynamic: project-url
Dynamic: requires-dist
Dynamic: requires-python
Dynamic: summary
